media4de-0.1.0.dist-info/licenses/LICENCE
media_edit/__init__.py
media_edit/add_text.py
media4de-0.1.0.dist-info/METADATA
media4de-0.1.0.dist-info/WHEEL
media4de-0.1.0.dist-info/top_level.txt
media4de-0.1.0.dist-info/RECORD
